azure/mgmt/networkanalytics/__init__.py
azure/mgmt/networkanalytics/_configuration.py
azure/mgmt/networkanalytics/_network_analytics_mgmt_client.py
azure/mgmt/networkanalytics/_patch.py
azure/mgmt/networkanalytics/_serialization.py
azure/mgmt/networkanalytics/_vendor.py
azure/mgmt/networkanalytics/_version.py
azure/mgmt/networkanalytics/py.typed
azure/mgmt/networkanalytics/aio/__init__.py
azure/mgmt/networkanalytics/aio/_configuration.py
azure/mgmt/networkanalytics/aio/_network_analytics_mgmt_client.py
azure/mgmt/networkanalytics/aio/_patch.py
azure/mgmt/networkanalytics/aio/operations/__init__.py
azure/mgmt/networkanalytics/aio/operations/_data_products_catalogs_operations.py
azure/mgmt/networkanalytics/aio/operations/_data_products_operations.py
azure/mgmt/networkanalytics/aio/operations/_data_types_operations.py
azure/mgmt/networkanalytics/aio/operations/_operations.py
azure/mgmt/networkanalytics/aio/operations/_patch.py
azure/mgmt/networkanalytics/models/__init__.py
azure/mgmt/networkanalytics/models/_models_py3.py
azure/mgmt/networkanalytics/models/_network_analytics_mgmt_client_enums.py
azure/mgmt/networkanalytics/models/_patch.py
azure/mgmt/networkanalytics/operations/__init__.py
azure/mgmt/networkanalytics/operations/_data_products_catalogs_operations.py
azure/mgmt/networkanalytics/operations/_data_products_operations.py
azure/mgmt/networkanalytics/operations/_data_types_operations.py
azure/mgmt/networkanalytics/operations/_operations.py
azure/mgmt/networkanalytics/operations/_patch.py
azure_mgmt_networkanalytics-1.0.0.dist-info/LICENSE
azure_mgmt_networkanalytics-1.0.0.dist-info/METADATA
azure_mgmt_networkanalytics-1.0.0.dist-info/WHEEL
azure_mgmt_networkanalytics-1.0.0.dist-info/top_level.txt
azure_mgmt_networkanalytics-1.0.0.dist-info/RECORD
